{"file":"mc_ty_dznnroom_icon_cjc.png","frames":{"img_ty_dznnroom_font_cjc7":{"y":40,"h":35,"offY":6,"offX":5,"w":109,"x":374},"img_ty_dznnroom_font_cjc6":{"y":77,"h":36,"offY":5,"offX":0,"w":96,"x":374},"img_ty_dznnroom_font_cjc11":{"y":212,"h":38,"offY":4,"offX":66,"w":60,"x":315},"img_ty_dznnroom_icon_cjc0":{"y":0,"h":217,"offY":0,"offX":0,"w":235,"x":0},"img_ty_dznnroom_font_cjc3":{"y":115,"h":36,"offY":5,"offX":0,"w":39,"x":469},"img_ty_dznnroom_font_cjc12":{"y":135,"h":38,"offY":4,"offX":81,"w":45,"x":315},"img_ty_dznnroom_font_cjc9":{"y":115,"h":38,"offY":4,"offX":33,"w":93,"x":374},"img_ty_dznnroom_font_cjc1":{"y":0,"h":19,"offY":5,"offX":0,"w":18,"x":485},"img_ty_dznnroom_font_cjc5":{"y":175,"h":36,"offY":5,"offX":0,"w":76,"x":237},"img_ty_dznnroom_font_cjc4":{"y":212,"h":36,"offY":5,"offX":0,"w":61,"x":377},"img_ty_dznnroom_font_cjc2":{"y":77,"h":33,"offY":5,"offX":0,"w":27,"x":472},"img_ty_dznnroom_icon_cjc_font":{"y":155,"h":55,"offY":4,"offX":1,"w":142,"x":362},"img_ty_dznnroom_font_cjc10":{"y":135,"h":38,"offY":4,"offX":50,"w":76,"x":237},"img_ty_dznnroom_font_cjc8":{"y":0,"h":38,"offY":4,"offX":14,"w":109,"x":374},"img_ty_dznnroom_icon_cjc1":{"y":0,"h":133,"offY":0,"offX":0,"w":135,"x":237}}}