{"file":"mc_th_room_yqnn_npc.png","frames":{"img_th_yqnnroom_npc_15":{"offX":0,"y":379,"h":82,"offY":0,"w":73,"x":386},"img_th_yqnnroom_npc_3":{"offX":0,"y":160,"h":119,"offY":0,"w":77,"x":398},"img_th_yqnnroom_npc_8":{"offX":0,"y":382,"h":99,"offY":0,"w":141,"x":228},"img_th_yqnnroom_npc_7":{"offX":0,"y":483,"h":45,"offY":0,"w":57,"x":225},"img_th_yqnnroom_npc_10":{"offX":0,"y":182,"h":153,"offY":0,"w":231,"x":0},"img_th_yqnnroom_npc_14":{"offX":0,"y":337,"h":79,"offY":0,"w":83,"x":143},"img_th_yqnnroom_npc_2":{"offX":0,"y":0,"h":158,"offY":0,"w":88,"x":398},"img_th_yqnnroom_npc_6":{"offX":0,"y":337,"h":171,"offY":0,"w":141,"x":0},"img_th_yqnnroom_npc_13":{"offX":0,"y":466,"h":25,"offY":0,"w":37,"x":457},"img_th_yqnnroom_npc_17":{"offX":0,"y":0,"h":180,"offY":0,"w":396,"x":0},"img_th_yqnnroom_npc_1":{"offX":0,"y":379,"h":85,"offY":0,"w":39,"x":461},"img_th_yqnnroom_npc_9":{"offX":0,"y":510,"h":132,"offY":0,"w":179,"x":0},"img_th_yqnnroom_npc_11":{"offX":0,"y":281,"h":96,"offY":0,"w":91,"x":386},"img_th_yqnnroom_npc_12":{"offX":0,"y":463,"h":26,"offY":0,"w":40,"x":415},"img_th_yqnnroom_npc_4":{"offX":0,"y":418,"h":73,"offY":0,"w":80,"x":143},"img_th_yqnnroom_npc_16":{"offX":0,"y":182,"h":198,"offY":0,"w":151,"x":233},"img_th_yqnnroom_npc_5":{"offX":0,"y":463,"h":64,"offY":0,"w":42,"x":371}}}